gsone/__init__.py
gsone/gsone.py
tests/__init__.py
tests/test_gsone.py
gsone-0.1.0.dist-info/METADATA
gsone-0.1.0.dist-info/WHEEL
gsone-0.1.0.dist-info/top_level.txt
gsone-0.1.0.dist-info/RECORD
